scadere/__init__.py
scadere/atom2xhtml.xslt
scadere/check.py
scadere/listen.py
scadere-0.2.4.dist-info/entry_points.txt
scadere-0.2.4.dist-info/licenses/LICENSES/AGPL-3.0-or-later.txt
scadere-0.2.4.dist-info/licenses/LICENSES/CC0-1.0.txt
scadere-0.2.4.dist-info/WHEEL
scadere-0.2.4.dist-info/METADATA
scadere-0.2.4.dist-info/RECORD
