Metadata-Version: 2.4
Name: scadere
Version: 0.2.4
Summary: TLS certificate renewal reminder
Keywords: atom,tls,ca
Author-email: Nguyễn Gia Phong <cnx@loang.net>
Maintainer-email: Nguyễn Gia Phong <chung@loa.loang.net>
Requires-Python: >=3.11
License-Expression: AGPL-3.0-or-later AND CC0-1.0
Classifier: Development Status :: 4 - Beta
Classifier: Environment :: Console
Classifier: Environment :: Web Environment
Classifier: Framework :: AsyncIO
Classifier: Operating System :: OS Independent
Classifier: Programming Language :: Python
Classifier: Topic :: Utilities
License-File: LICENSES/AGPL-3.0-or-later.txt
License-File: LICENSES/CC0-1.0.txt
Requires-Dist: coverage ; extra == "dev"
Requires-Dist: flake8 ; extra == "dev"
Requires-Dist: hypothesis ; extra == "dev"
Requires-Dist: pytest ; extra == "dev"
Requires-Dist: pytest-asyncio ; extra == "dev"
Requires-Dist: reuse ; extra == "dev"
Requires-Dist: trustme >= 1.2.0 ; extra == "dev"
Project-URL: Inbox, https://loa.loang.net/chung
Project-URL: Source, https://trong.loang.net/scadere
Provides-Extra: dev
